wisort/cli.py
wisort/characters/__init__.py
wisort/config/__init__.py
wisort/files/__init__.py
wisort/files/conflicts.py
wisort/files/dedupe.py
wisort/files/move.py
wisort/files/sort.py
wisort/files/utils.py
wisort/runes/__init__.py
wisort-0.3.0.dist-info/METADATA
wisort-0.3.0.dist-info/WHEEL
wisort-0.3.0.dist-info/entry_points.txt
wisort-0.3.0.dist-info/licenses/LICENSE
wisort-0.3.0.dist-info/RECORD
