Metadata-Version: 2.4
Name: wisort
Version: 0.3.0
Summary: A system to sort your files
Project-URL: Repository, https://github.com/vividsystem/wisort
Author: vividsystem
License: MIT License
License-File: LICENSE
Requires-Python: >=3.14
Requires-Dist: blake3>=1.0.7
Requires-Dist: pathspec>=0.12.1
Requires-Dist: pydantic>=2.12.0
Requires-Dist: questionary>=2.1.1
Requires-Dist: typer>=0.19.2
